ShowTkProssBar2/__init__.py
ShowTkProssBar2-0.0.2.dist-info/LICENSE
ShowTkProssBar2-0.0.2.dist-info/METADATA
ShowTkProssBar2-0.0.2.dist-info/WHEEL
ShowTkProssBar2-0.0.2.dist-info/top_level.txt
ShowTkProssBar2-0.0.2.dist-info/RECORD
