Metadata-Version: 2.1
Name: ShowTkProssBar2
Version: 0.0.2
Summary: show a tk prossbar
Home-page: https://44202439.org
Author: glwwanggs
Author-email: 442024339@qq.com
License: UNKNOWN
Platform: UNKNOWN
Requires-Python: >=3.6
